[
  {
    "name": "🛁Bathhouse",
    "access_rules": ["@Ducky Bathroom/Exit to Flooded House"],
    "children": [
      {
        "name": "Locker Room",
        "sections": [{"name": "Locker", "item_count": 1}]
      },
      {
        "name": "Pool",
        "sections": [
          {
            "name": "Middle Drain",
            "hosted_item": "artifact_d20"
          }
        ],
        "map_locations": [{"map": "bathhouse", "x": 340, "y": 400}]
      },
      {
        "name": "Shattered Path",
        "sections": [
          {
            "name": "Remote Pedestal",
            "hosted_item": "artifact_ring"
          }
        ],
        "map_locations": [{"map": "bathhouse", "x": 515, "y": 110}]
      },
      {
        "name": "Bathhouse: Exit to Brutalist House",
        "sections": [{"name": "Exit", "item_count": 1}],
        "map_locations": [
          {"map": "overworld", "x": 272, "y": 488},
          {"map": "bathhouse", "x": 390, "y": 0}
        ]
      }
    ]
  }
]
