[
  {
    "name": "⛽Gas Station",
    "access_rules": ["@Passage/Exit to Gas Station"],
    "children": [
      {
        "name": "Tree",
        "sections": [
          {
            "name": "Ending 3",
            "access_rules": ["mirrorgasstation_treeheart"],
            "hosted_item": "ending3"
          }
        ],
        "map_locations": [
          {"map": "overworld", "x": 234, "y": 528},
          {"map": "gasstation", "x": 95, "y": 75}
        ]
      },
      {
        "name": "Sludgie Machine",
        "sections": [
          {
            "name": "Baby",
            "visibility_rules": ["difficulty_baby"],
            "hosted_item": "sludgie_baby"
          },
          {
            "name": "Easy",
            "visibility_rules": ["difficulty_easy"],
            "hosted_item": "sludgie_easy"
          },
          {
            "name": "Medium",
            "visibility_rules": ["difficulty_medium"],
            "hosted_item": "sludgie_medium"
          },
          {
            "name": "Hard",
            "visibility_rules": ["difficulty_hard"],
            "hosted_item": "sludgie_hard"
          },
          {
            "name": "Nightmare",
            "visibility_rules": ["difficulty_nightmare"],
            "hosted_item": "sludgie_nightmare"
          }
        ],
        "map_locations": [{"map": "gasstation", "x": 750, "y": 360}]
      },
      {
        "name": "Closet",
        "sections": [
          {
            "name": "Video Game Controller",
            "hosted_item": "artifact_gamecontroller"
          }
        ],
        "map_locations": [{"map": "gasstation", "x": 710, "y": 325}]
      },
      {
        "name": "Bathroom",
        "sections": [
          {"name": "Exit to Second House", "item_count": 1}
        ],
        "map_locations": [{"map": "gasstation", "x": 750, "y": 330}]
      }
    ]
  }
]
